odoo/addons/ssi_rent/README.rst
odoo/addons/ssi_rent/__init__.py
odoo/addons/ssi_rent/__manifest__.py
odoo/addons/ssi_rent/menu.xml
odoo/addons/ssi_rent/models/__init__.py
odoo/addons/ssi_rent/models/rent_order.py
odoo/addons/ssi_rent/models/rent_order_payment_schedule.py
odoo/addons/ssi_rent/models/rent_type.py
odoo/addons/ssi_rent/models/res_company.py
odoo/addons/ssi_rent/models/res_config_settings.py
odoo/addons/ssi_rent/security/ir_module_category_data.xml
odoo/addons/ssi_rent/static/description/icon.png
odoo/addons/ssi_rent/views/rent_order_views.xml
odoo/addons/ssi_rent/views/rent_type_views.xml
odoo14_addon_ssi_rent-14.0.2.0.0.dist-info/METADATA
odoo14_addon_ssi_rent-14.0.2.0.0.dist-info/WHEEL
odoo14_addon_ssi_rent-14.0.2.0.0.dist-info/top_level.txt
odoo14_addon_ssi_rent-14.0.2.0.0.dist-info/RECORD
