Metadata-Version: 2.1
Name: odoo14-addon-ssi-rent
Version: 14.0.2.0.0
Summary: Rent Management
Home-page: https://simetri-sinergi.id
Author: OpenSynergy Indonesia, PT. Simetri Sinergi Indonesia
License: AGPL-3
Platform: UNKNOWN
Classifier: Programming Language :: Python
Classifier: Framework :: Odoo
Classifier: Framework :: Odoo :: 14.0
Classifier: License :: OSI Approved :: GNU Affero General Public License v3
Requires-Python: >=3.6
Requires-Dist: odoo14-addon-base-duration
Requires-Dist: odoo14-addon-configuration-helper
Requires-Dist: odoo14-addon-ssi-company-currency-mixin
Requires-Dist: odoo14-addon-ssi-financial-accounting
Requires-Dist: odoo14-addon-ssi-localdict-mixin
Requires-Dist: odoo14-addon-ssi-m2o-configurator-mixin
Requires-Dist: odoo14-addon-ssi-master-data-mixin
Requires-Dist: odoo14-addon-ssi-product-line-account-mixin
Requires-Dist: odoo14-addon-ssi-transaction-cancel-mixin
Requires-Dist: odoo14-addon-ssi-transaction-confirm-mixin
Requires-Dist: odoo14-addon-ssi-transaction-date-duration-mixin
Requires-Dist: odoo14-addon-ssi-transaction-done-mixin
Requires-Dist: odoo14-addon-ssi-transaction-open-mixin
Requires-Dist: odoo14-addon-ssi-transaction-partner-mixin
Requires-Dist: odoo14-addon-ssi-transaction-pricelist-mixin
Requires-Dist: odoo14-addon-ssi-transaction-ready-mixin
Requires-Dist: odoo14-addon-ssi-transaction-terminate-mixin
Requires-Dist: odoo (<14.1dev,>=14.0a)
